mjeffryes_command/__init__.py
mjeffryes_command/_utilities.py
mjeffryes_command/provider.py
mjeffryes_command/pulumi-plugin.json
mjeffryes_command/py.typed
mjeffryes_command/local/__init__.py
mjeffryes_command/local/_enums.py
mjeffryes_command/local/command.py
mjeffryes_command/local/run.py
mjeffryes_command/remote/__init__.py
mjeffryes_command/remote/_enums.py
mjeffryes_command/remote/_inputs.py
mjeffryes_command/remote/command.py
mjeffryes_command/remote/copy_file.py
mjeffryes_command/remote/copy_to_remote.py
mjeffryes_command/remote/outputs.py
mjeffryes_command-0.0.1a5.dist-info/METADATA
mjeffryes_command-0.0.1a5.dist-info/WHEEL
mjeffryes_command-0.0.1a5.dist-info/top_level.txt
mjeffryes_command-0.0.1a5.dist-info/RECORD
