Metadata-Version: 2.4
Name: mjeffryes_command
Version: 0.0.1a5
Summary: The Pulumi Command Provider enables you to execute commands and scripts either locally or remotely as part of the Pulumi resource model.
License: Apache-2.0
Project-URL: Homepage, https://pulumi.com
Project-URL: Repository, https://github.com/pulumi/pulumi-command
Keywords: pulumi,command,category/utility,kind/native
Requires-Python: >=3.9
Requires-Dist: parver>=0.2.1
Requires-Dist: pulumi<4.0.0,>=3.142.0
Requires-Dist: semver>=2.8.1
Requires-Dist: typing-extensions>=4.11; python_version < "3.11"
